.gitignore
CHANGELOG.md
LICENSE
README.md
entry_points.ini
requirements.in
requirements.txt
setup.py
version
dashboards/iMessage/README.md
dashboards/iMessage/iMessage.twb
graphics/logo.icns
graphics/logo.png
src/__init__.py
src/app.py
src/cli.py
src/app_reference/app_param_overrides.yaml
src/app_reference/pydoni_location.txt
src/cli_reference/common.py
src/commands/cli_audio.py
src/commands/cli_data.py
src/commands/cli_image.py
src/commands/cli_imessage.py
src/commands/cli_movie.py
src/commands/cli_notes.py
src/commands/cli_opsys.py
src/commands/cli_photo.py
src/commands/cli_video.py
src/commands/audio/compress_file.py
src/commands/audio/join_files.py
src/commands/audio/m4a_to_mp3.py
src/commands/audio/text_to_speech.py
src/commands/data/append_backup_log_table.py
src/commands/data/backup.py
src/commands/data/pg_dump.py
src/commands/data/.archive/git_sync.py
src/commands/image/ocr.py
src/commands/imessage/workflow_elt/extract.py
src/commands/imessage/workflow_elt/load.py
src/commands/imessage/workflow_elt/transform.py
src/commands/imessage/workflow_elt/workflow_elt.py
src/commands/imessage/workflow_elt/data_quality/append_new_rowids_to_map_tables.sql
src/commands/imessage/workflow_elt/db_views/db_views.py
src/commands/imessage/workflow_elt/db_views/view_defs/attachment_full_history_vw.sql
src/commands/imessage/workflow_elt/db_views/view_defs/chat_full_history_vw.sql
src/commands/imessage/workflow_elt/db_views/view_defs/chat_handle_join_full_history_vw.sql
src/commands/imessage/workflow_elt/db_views/view_defs/chat_message_join_full_history_vw.sql
src/commands/imessage/workflow_elt/db_views/view_defs/contact_daily_message_volume_vw.sql
src/commands/imessage/workflow_elt/db_views/view_defs/contact_names_vw.sql
src/commands/imessage/workflow_elt/db_views/view_defs/contact_token_usage_vw.sql
src/commands/imessage/workflow_elt/db_views/view_defs/contact_top_token_usage_by_length.sql
src/commands/imessage/workflow_elt/db_views/view_defs/handle_full_history_vw.sql
src/pydonicli.egg-info/PKG-INFO
src/pydonicli.egg-info/SOURCES.txt
src/pydonicli.egg-info/dependency_links.txt
src/pydonicli.egg-info/entry_points.txt
src/pydonicli.egg-info/requires.txt
src/pydonicli.egg-info/top_level.txt
