Metadata-Version: 2.1
Name: pydonicli
Version: 0.2.5
Summary: pydoni-cli is a Python library that serves as a command-line interface to custom-built tools developed by Andoni Sooklaris.
Home-page: https://github.com/tsouchlarakis/pydoni-cli
Author: Andoni Sooklaris
Author-email: andoni.sooklaris@gmail.com
License: Copyright (c) 2020-2021 Andoni Sooklaris
Platform: UNKNOWN
